glue_geospatial/__init__.py
glue_geospatial/coordinates.py
glue_geospatial/data_factory.py
glue_geospatial/tests/__init__.py
glue_geospatial/tests/test_basic.py
glue_geospatial/tests/data/generate.py
glue_geospatial/tests/data/plain.tif
glue_geospatial/tests/data/simplegeo.tif
glue_geospatial-0.4.dist-info/LICENSE
glue_geospatial-0.4.dist-info/METADATA
glue_geospatial-0.4.dist-info/WHEEL
glue_geospatial-0.4.dist-info/entry_points.txt
glue_geospatial-0.4.dist-info/top_level.txt
glue_geospatial-0.4.dist-info/zip-safe
glue_geospatial-0.4.dist-info/RECORD
