Metadata-Version: 2.1
Name: glue-geospatial
Version: 0.4
Summary: Experimental glue plugin for geospatial imagery
Home-page: https://github.com/glue-viz/glue-geospatial
Author: Thomas Robitaille
Author-email: thomas.robitaille@gmail.com
License: UNKNOWN
Platform: UNKNOWN
Requires-Python: >=3.6
Requires-Dist: glue-core (>=1.0)
Requires-Dist: rasterio (>=1.0)
Requires-Dist: pyproj (>=2.3)
Requires-Dist: affine
Provides-Extra: test
Requires-Dist: pytest ; extra == 'test'
Requires-Dist: pytest-cov ; extra == 'test'
Requires-Dist: pytest-faulthandler ; extra == 'test'
Requires-Dist: mock ; extra == 'test'
